turbocow/__init__.py
turbocow/example.py
turbocow-0.0.2.dist-info/LICENSE
turbocow-0.0.2.dist-info/METADATA
turbocow-0.0.2.dist-info/WHEEL
turbocow-0.0.2.dist-info/top_level.txt
turbocow-0.0.2.dist-info/RECORD
