Metadata-Version: 2.1
Name: turbocow
Version: 0.0.2
Summary: new age of python web frameworks
Author: zuczekgnojak
Classifier: Programming Language :: Python :: 3
Classifier: License :: OSI Approved :: MIT License
Classifier: Operating System :: OS Independent
Requires-Python: >=3.10
License-File: LICENSE
